<annotation>
    <folder>output</folder>
    <filename>24-02.jpg</filename>
    <path>D:\PythonPrograms\DishRecognition\bounding-box-augmentation-master\output\24-02.jpg</path>
    <source>
        <database>Unknown</database>
    </source>
    <size>
        <width>800</width>
        <height>600</height>
        <depth>3</depth>
    </size>
    <segmented>0</segmented>
    <object>
        <name>dish11</name>
        <pose>Unspecified</pose>
        <truncated>0</truncated>
        <difficult>0</difficult>
        <bndbox>
            <xmin>147</xmin>
            <ymin>218</ymin>
            <xmax>383</xmax>
            <ymax>475</ymax>
        </bndbox>
    </object>
</annotation>
